{ "compressionlevel":-1,
 "editorsettings":
    {
     "export":
        {
         "format":"json",
         "target":"SafariZoo.json"
        }
    },
 "height":25,
 "infinite":false,
 "layers":[
        {
         "data":[1, 1, 1, 1, 1, 1, 1, 1, 1, 1, 1, 1, 1, 1, 1, 1, 1, 1, 1, 1, 1, 1, 1, 1, 1, 1, 1, 1, 1, 1, 1, 1, 1, 1, 1, 1, 1, 1, 1, 1, 1, 1, 1, 1, 1, 1, 1, 1, 1, 1, 1, 1, 1, 1, 1, 1, 1, 1, 1, 1, 1, 1, 1, 1, 1, 1, 1, 1, 1, 1, 1, 1, 1, 1, 1, 1, 1, 1, 1, 1, 1, 1, 1, 1, 1, 1, 1, 1, 1, 1, 1, 1, 1, 1, 1, 1, 1, 1, 1, 1, 1, 1, 1, 1, 2, 1, 1, 1, 1, 1, 1, 1, 1, 1, 1, 1, 1, 1, 1, 1, 1, 1, 1, 1, 1, 1, 1, 1, 1, 1, 1, 1, 1, 1, 1, 1, 1, 1, 1, 1, 1, 1, 1, 1, 1, 1, 1, 1, 1, 1, 1, 1, 1, 1, 1, 1, 1, 1, 1, 1, 2, 1, 1, 1, 1, 1, 1, 1, 1, 1, 1, 1, 1, 1, 1, 1, 1, 1, 1, 1, 1, 1, 1, 1, 1, 1, 1, 1, 1, 1, 1, 1, 1, 1, 1, 1, 1, 1, 1, 1, 1, 1, 1, 1, 1, 1, 2, 1, 1, 1, 1, 1, 1, 1, 1, 1, 1, 1, 1, 1, 1, 1, 1, 1, 1, 1, 1, 1, 1, 1, 1, 1, 1, 1, 1, 1, 1, 1, 1, 1, 1, 1, 1, 1, 1, 1, 1, 1, 1, 1, 1, 1, 1, 1, 1, 1, 1, 1, 1, 1, 2, 2, 2, 1, 1, 1, 1, 1, 1, 1, 1, 1, 1, 1, 1, 1, 1, 1, 1, 1, 1, 1, 1, 1, 1, 1, 1, 1, 1, 1, 1, 1, 1, 1, 1, 1, 1, 1, 2, 16, 2, 1, 1, 1, 1, 1, 1, 1, 2, 1, 1, 1, 1, 1, 1, 1, 1, 1, 1, 1, 1, 1, 1, 1, 1, 1, 1, 1, 1, 1, 1, 1, 1, 1, 1, 1, 2, 2, 2, 1, 1, 1, 1, 1, 1, 1, 1, 1, 1, 1, 1, 1, 1, 1, 1, 1, 1, 1, 1, 1, 1, 1, 1, 1, 1, 1, 1, 1, 1, 2, 1, 1, 1, 1, 1, 1, 1, 1, 1, 1, 1, 1, 1, 1, 1, 1, 1, 1, 1, 1, 1, 1, 1, 1, 1, 1, 1, 1, 1, 1, 1, 1, 1, 1, 1, 1, 1, 1, 1, 1, 1, 1, 1, 1, 1, 1, 1, 1, 1, 1, 1, 1, 1, 1, 1, 1, 1, 1, 1, 1, 1, 2, 1, 1, 1, 1, 1, 1, 2, 1, 1, 1, 1, 1, 1, 1, 1, 1, 1, 1, 1, 1, 1, 1, 1, 1, 1, 1, 1, 1, 1, 2, 1, 1, 1, 1, 1, 1, 1, 1, 1, 1, 1, 1, 1, 1, 1, 1, 1, 1, 1, 1, 1, 1, 1, 1, 1, 1, 1, 2, 1, 1, 1, 1, 1, 1, 1, 1, 1, 1, 1, 1, 1, 1, 1, 1, 1, 1, 1, 1, 1, 1, 1, 1, 1, 1, 1, 1, 1, 1, 1, 1, 1, 1, 1, 1, 1, 1, 1, 1, 1, 1, 1, 1, 1, 1, 1, 1, 1, 1, 1, 1, 1, 1, 1, 1, 1, 1, 1, 1, 1, 1, 1, 1, 1, 1, 1, 1, 1, 1, 1, 1, 1, 1, 1, 1, 1, 1, 1, 1, 1, 1, 1, 2, 1, 1, 1, 1, 1, 1, 1, 1, 1, 1, 1, 1, 1, 1, 1, 1, 1, 1, 1, 1, 1, 1, 1, 1, 1, 1, 1, 1, 1, 1, 1, 1, 1, 1, 1, 1, 1, 1, 1, 1, 1, 1, 1, 1, 1, 2, 1, 1, 1, 1, 1, 1, 1, 1, 1, 1, 1, 1, 1, 1, 1, 1, 1, 1, 1, 1, 1, 1, 1, 1, 1, 1, 1, 1, 1, 1, 1, 1, 1, 1, 1, 1, 1, 1, 1, 1, 1, 1, 1, 1, 1, 1, 1, 1, 1, 1, 1, 1, 1, 1, 1, 1, 2, 2, 2, 1, 1, 1, 1, 1, 1, 1, 1, 1, 1, 1, 1, 1, 1, 1, 1, 1, 1, 1, 1, 1, 1, 1, 1, 1, 1, 1, 1, 1, 1, 1, 1, 1, 1, 1, 2, 16, 2, 1, 1, 1, 1, 1, 1, 1, 1, 1, 1, 2, 1, 1, 1, 1, 1, 1, 1, 1, 1, 1, 1, 1, 1, 1, 1, 1, 1, 1, 1, 1, 1, 1, 1, 1, 2, 2, 2, 1, 1, 1, 1, 1, 1, 1, 1, 1, 1, 1, 1, 1, 1, 1, 1, 1, 1, 1, 1, 2, 1, 1, 1, 1, 1, 1, 1, 1, 1, 1, 1, 1, 1, 1, 1, 1, 1, 1, 1, 2, 1, 1, 1, 1, 1, 1, 1, 1, 1, 1, 1, 1, 1, 1, 1, 1, 1, 1, 1, 1, 1, 1, 1, 1, 1, 1, 1, 1, 1, 1, 1, 1, 1, 1, 1, 1, 1, 1, 1, 1, 1, 1, 1, 2, 1, 1, 1, 1, 1, 1, 1, 1, 1, 1, 1, 1, 1, 1, 1, 1, 1, 1, 1, 1, 1, 1, 1, 1, 1, 1, 1, 1, 1, 1, 1, 1, 1, 1, 1, 1, 1, 1, 1, 1, 1, 1, 1, 1, 1, 1, 1, 1, 1, 1, 1, 1, 1, 1, 1, 1, 1, 1, 1, 1, 1, 1, 2, 1, 1, 1, 1, 1, 1, 1, 1, 1, 1, 1, 1, 1, 1, 1, 1, 1, 1, 1, 1, 1, 1, 1, 1, 1, 1, 1, 1, 1, 1, 1, 1, 1, 1, 1, 1, 1, 1, 1, 1, 1, 1, 1, 1, 1, 1, 1],
         "height":25,
         "id":1,
         "name":"Floor",
         "opacity":1,
         "properties":[
                {
                 "name":"Collidable",
                 "type":"bool",
                 "value":false
                }],
         "type":"tilelayer",
         "visible":true,
         "width":38,
         "x":0,
         "y":0
        }, 
        {
         "data":[8, 7, 7, 7, 7, 7, 7, 7, 7, 7, 7, 7, 7, 7, 7, 7, 7, 7, 7, 7, 7, 7, 7, 7, 7, 13, 0, 0, 0, 0, 0, 0, 0, 0, 0, 0, 0, 0, 5, 3, 3, 3, 3, 3, 3, 3, 3, 3, 3, 3, 3, 3, 3, 3, 3, 3, 3, 3, 3, 3, 3, 3, 3, 4, 0, 0, 0, 0, 0, 0, 0, 0, 0, 0, 0, 0, 5, 3, 10, 6, 6, 6, 6, 6, 6, 6, 6, 6, 6, 6, 6, 6, 6, 6, 6, 6, 6, 6, 6, 9, 3, 4, 0, 0, 0, 0, 0, 0, 0, 0, 0, 0, 0, 0, 5, 3, 4, 0, 0, 0, 0, 0, 0, 0, 0, 0, 0, 0, 0, 0, 0, 0, 0, 0, 0, 0, 0, 5, 3, 4, 0, 0, 0, 0, 0, 0, 0, 0, 0, 0, 0, 0, 5, 3, 4, 0, 0, 0, 0, 0, 0, 0, 0, 0, 0, 0, 0, 0, 0, 0, 0, 0, 0, 0, 0, 5, 3, 4, 0, 0, 0, 0, 0, 0, 0, 0, 0, 0, 0, 0, 5, 3, 4, 0, 0, 0, 0, 0, 0, 0, 0, 0, 0, 0, 0, 0, 0, 0, 0, 0, 0, 0, 0, 5, 3, 4, 0, 0, 0, 0, 0, 0, 0, 0, 0, 0, 0, 0, 5, 3, 4, 0, 0, 0, 0, 8, 7, 7, 7, 7, 7, 7, 7, 7, 7, 7, 13, 0, 0, 0, 0, 5, 3, 4, 0, 0, 0, 0, 0, 0, 0, 0, 0, 0, 0, 0, 5, 3, 4, 0, 0, 0, 0, 5, 3, 3, 3, 3, 3, 3, 3, 3, 3, 3, 4, 0, 0, 0, 0, 5, 3, 4, 0, 0, 0, 0, 0, 0, 0, 0, 0, 0, 0, 0, 5, 3, 4, 0, 0, 0, 0, 5, 3, 10, 6, 6, 6, 6, 6, 6, 9, 3, 4, 0, 0, 0, 0, 5, 3, 4, 0, 0, 0, 0, 0, 0, 0, 0, 0, 0, 0, 0, 5, 3, 4, 0, 0, 0, 0, 5, 3, 4, 0, 0, 0, 0, 0, 0, 5, 3, 4, 0, 0, 0, 0, 5, 3, 4, 0, 0, 0, 0, 0, 0, 0, 0, 0, 0, 0, 0, 5, 3, 4, 0, 0, 0, 0, 5, 3, 4, 0, 0, 0, 0, 0, 0, 5, 3, 4, 0, 0, 0, 0, 5, 3, 4, 0, 0, 0, 0, 0, 0, 0, 0, 0, 0, 0, 0, 5, 3, 4, 0, 0, 0, 0, 5, 3, 4, 0, 0, 0, 0, 0, 0, 5, 3, 4, 0, 0, 0, 0, 5, 3, 4, 0, 0, 0, 0, 0, 0, 0, 0, 0, 0, 0, 0, 5, 3, 4, 0, 0, 0, 0, 5, 3, 4, 0, 0, 0, 0, 0, 0, 5, 3, 4, 0, 0, 0, 0, 5, 3, 4, 0, 0, 0, 0, 0, 0, 0, 0, 0, 0, 0, 0, 5, 3, 4, 0, 0, 0, 0, 5, 3, 4, 0, 0, 0, 0, 0, 8, 11, 3, 12, 13, 0, 0, 0, 5, 3, 4, 0, 0, 0, 0, 0, 0, 0, 0, 0, 0, 0, 0, 5, 3, 4, 0, 0, 0, 0, 5, 3, 4, 0, 0, 0, 0, 0, 5, 16, 2, 2, 4, 0, 0, 0, 5, 3, 4, 0, 0, 0, 0, 0, 0, 0, 0, 0, 0, 0, 0, 5, 3, 4, 0, 0, 0, 0, 5, 3, 4, 0, 0, 0, 0, 0, 5, 2, 16, 16, 4, 0, 0, 0, 5, 3, 4, 0, 0, 0, 0, 0, 0, 0, 0, 0, 0, 0, 0, 5, 3, 4, 0, 0, 0, 0, 5, 3, 4, 0, 0, 0, 0, 0, 15, 6, 6, 6, 14, 0, 0, 0, 5, 3, 4, 0, 0, 0, 0, 0, 0, 0, 0, 0, 0, 0, 0, 5, 3, 4, 0, 0, 0, 0, 5, 3, 4, 0, 0, 0, 0, 0, 0, 0, 0, 0, 0, 0, 0, 0, 5, 3, 4, 0, 0, 0, 0, 0, 0, 0, 0, 0, 0, 0, 0, 5, 3, 4, 0, 0, 0, 0, 5, 3, 4, 0, 0, 0, 0, 0, 0, 0, 0, 0, 0, 0, 0, 0, 5, 3, 4, 0, 0, 0, 0, 0, 0, 0, 0, 0, 0, 0, 0, 5, 3, 4, 0, 0, 0, 0, 5, 3, 4, 0, 0, 0, 0, 0, 0, 0, 0, 0, 0, 0, 0, 0, 5, 3, 4, 0, 0, 0, 0, 0, 0, 0, 0, 0, 0, 0, 0, 5, 3, 4, 0, 0, 0, 0, 5, 3, 4, 0, 0, 0, 0, 0, 0, 0, 0, 0, 0, 0, 0, 0, 5, 3, 4, 0, 0, 0, 0, 0, 0, 0, 0, 0, 0, 0, 0, 5, 3, 4, 0, 0, 0, 0, 5, 3, 12, 7, 7, 7, 7, 7, 7, 7, 7, 7, 7, 7, 7, 7, 11, 3, 4, 0, 0, 0, 0, 0, 0, 0, 0, 0, 0, 0, 0, 5, 3, 4, 0, 0, 0, 0, 5, 3, 3, 3, 3, 3, 3, 3, 3, 3, 3, 3, 3, 3, 3, 3, 3, 3, 4, 0, 0, 0, 0, 0, 0, 0, 0, 0, 0, 0, 0, 5, 3, 4, 0, 0, 0, 0, 15, 6, 6, 6, 6, 6, 6, 6, 6, 6, 6, 6, 6, 6, 6, 6, 6, 6, 14, 0, 0, 0, 0, 0, 0, 0, 0, 0, 0, 0, 0, 5, 3, 4, 0, 0, 0, 0, 0, 0, 0, 0, 0, 0, 0, 0, 0, 0, 0, 0, 0, 0, 0, 0, 0, 0, 0, 0, 0, 0, 0, 0, 0, 0, 0, 0, 0, 0, 0],
         "height":25,
         "id":2,
         "name":"EnemyArea",
         "opacity":1,
         "properties":[
                {
                 "name":"Collidable",
                 "type":"bool",
                 "value":true
                }, 
                {
                 "name":"Group",
                 "type":"string",
                 "value":"enemyPath"
                }],
         "type":"tilelayer",
         "visible":true,
         "width":38,
         "x":0,
         "y":0
        }],
 "nextlayerid":3,
 "nextobjectid":1,
 "orientation":"orthogonal",
 "renderorder":"right-down",
 "tiledversion":"1.4.3",
 "tileheight":16,
 "tilesets":[
        {
         "columns":5,
         "firstgid":1,
         "image":"SafariZooTiles.png",
         "imageheight":64,
         "imagewidth":80,
         "margin":0,
         "name":"SafariZooTiles",
         "spacing":0,
         "tilecount":20,
         "tileheight":16,
         "tilewidth":16
        }],
 "tilewidth":16,
 "type":"map",
 "version":1.4,
 "width":38
}